fine_python_format/__init__.py
fine_python_format/preset.toml
fine_python_format-0.3.0.dist-info/METADATA
fine_python_format-0.3.0.dist-info/WHEEL
fine_python_format-0.3.0.dist-info/top_level.txt
fine_python_format-0.3.0.dist-info/RECORD
